<?xml version="1.0" encoding="utf-8" ?>
<dwsync>
<file name="172WEB511-Final-Project.zip" server="ftp.frankjamison.com/htdocs/frankjamison/" local="131668740000000000" remote="131668740000000000" Dst="1" />
<file name="172WEB511-Guessing-Game.zip" server="ftp.frankjamison.com/htdocs/frankjamison/" local="131668740000000000" remote="131668740000000000" Dst="1" />
<file name="171WEB501-Final-Project.zip" server="ftp.frankjamison.com/htdocs/frankjamison/" local="131668740000000000" remote="131668740000000000" Dst="1" />
<file name="173WEB512-Final-Project.zip" server="ftp.frankjamison.com/htdocs/frankjamison/" local="131668740000000000" remote="131668740000000000" Dst="1" />
<file name="JavaScript-Stat-Roller.zip" server="ftp.frankjamison.com/htdocs/frankjamison/" local="131674788000000000" remote="131674788000000000" Dst="1" />
<file name="Lynda-CSS-Essential-Training-Project.zip" server="ftp.frankjamison.com/htdocs/frankjamison/" local="131682564000000000" remote="131682564000000000" Dst="1" />
<file name="Lynda-JavaScript-Essential-Training-Analog-Clock-Project.zip" server="ftp.frankjamison.com/htdocs/frankjamison/" local="131685156000000000" remote="131685156000000000" Dst="1" />
<file name="171WEB501-Final-Project.zip" server="D:/wamp/www/frankjamison2018/" local="131668639136691775" remote="131668639130000000" Dst="2" />
<file name="172WEB511-Final-Project.zip" server="D:/wamp/www/frankjamison2018/" local="131668637538848082" remote="131668637530000000" Dst="2" />
<file name="172WEB511-Guessing-Game.zip" server="D:/wamp/www/frankjamison2018/" local="131668639324902916" remote="131668639320000000" Dst="2" />
<file name="173WEB512-Final-Project.zip" server="D:/wamp/www/frankjamison2018/" local="131668662593932459" remote="131668662590000000" Dst="2" />
<file name="JavaScript-Stat-Roller.zip" server="D:/wamp/www/frankjamison2018/" local="131675209564910577" remote="131675209560000000" Dst="2" />
<file name="Lynda-CSS-Essential-Training-Project.zip" server="D:/wamp/www/frankjamison2018/" local="131682574431200428" remote="131682574430000000" Dst="2" />
<file name="Lynda-JavaScript-Essential-Training-Analog-Clock-Project.zip" server="D:/wamp/www/frankjamison2018/" local="131684982300201287" remote="131684982300000000" Dst="2" />
<file name="Lynda-JavaScript-Essential-Training-Typing-Speed-Tester.zip" server="ftp.frankjamison.com/htdocs/frankjamison/" local="131687748000000000" remote="131687748000000000" Dst="1" />
<file name="Lynda-JavaScript-Essential-Training-Responsive-Images-Project.zip" server="ftp.frankjamison.com/htdocs/frankjamison/" local="131688612000000000" remote="131688612000000000" Dst="1" />
<file name="174WEB515-Final-Project.zip" server="ftp.frankjamison.com/htdocs/frankjamison/" local="131749092000000000" remote="131749092000000000" Dst="1" />
<file name="Lynda-PHP-with-MySQL-Essential-Training.zip" server="ftp.frankjamison.com/htdocs/frankjamison/" local="131772927600000000" remote="131772927600000000" Dst="1" />
</dwsync>